setup.py
sampled_distributions/Binomialdistribution.py
sampled_distributions/Gaussiandistribution.py
sampled_distributions/Generaldistribution.py
sampled_distributions/__init__.py
sampled_distributions.egg-info/PKG-INFO
sampled_distributions.egg-info/SOURCES.txt
sampled_distributions.egg-info/dependency_links.txt
sampled_distributions.egg-info/not-zip-safe
sampled_distributions.egg-info/top_level.txt