Metadata-Version: 1.0
Name: sampled-distributions
Version: 0.2
Summary: General, Gaussian and Binomial distributions
Home-page: UNKNOWN
Author: Victor Mochengo
Author-email: victormochengo@gmail.com
License: UNKNOWN
Platform: UNKNOWN
